PygameShader/BlendFlags.cp38-win32.pyd
PygameShader/BlendFlags.cpp
PygameShader/BlendFlags.pxd
PygameShader/BlendFlags.pyx
PygameShader/BurstSurface.cp38-win32.pyd
PygameShader/BurstSurface.cpp
PygameShader/BurstSurface.pxd
PygameShader/BurstSurface.pyx
PygameShader/Dithering.py
PygameShader/Fire.cp38-win32.pyd
PygameShader/Fire.cpp
PygameShader/Fire.pxd
PygameShader/Fire.pyx
PygameShader/Palette.cp38-win32.pyd
PygameShader/Palette.cpp
PygameShader/Palette.pxd
PygameShader/Palette.pyx
PygameShader/PygameTools.cp38-win32.pyd
PygameShader/PygameTools.cpp
PygameShader/PygameTools.pxd
PygameShader/PygameTools.pyx
PygameShader/RGBConvert.cp38-win32.pyd
PygameShader/RGBConvert.cpp
PygameShader/RGBConvert.pxd
PygameShader/RGBConvert.pyx
PygameShader/Sprites.cp38-win32.pyd
PygameShader/Sprites.cpp
PygameShader/Sprites.pxd
PygameShader/Sprites.pyx
PygameShader/__init__.pxd
PygameShader/__init__.py
PygameShader/config.py
PygameShader/gaussianBlur5x5.cp38-win32.pyd
PygameShader/gaussianBlur5x5.cpp
PygameShader/gaussianBlur5x5.pxd
PygameShader/gaussianBlur5x5.pyx
PygameShader/misc.cp38-win32.pyd
PygameShader/misc.cpp
PygameShader/misc.pxd
PygameShader/misc.pyx
PygameShader/setup_shader.py
PygameShader/shader.cp38-win32.pyd
PygameShader/shader.cpp
PygameShader/shader.pxd
PygameShader/shader.pyx
PygameShader/shader_gpu.cp38-win32.pyd
PygameShader/shader_gpu.cpp
PygameShader/shader_gpu.pxd
PygameShader/shader_gpu.pyx
PygameShader/Assets/Aliens.jpg
PygameShader/Assets/AliensLuma.png
PygameShader/Assets/Bokeh__Lens_Dirt_38.jpg
PygameShader/Assets/Bokeh__Lens_Dirt_46.jpg
PygameShader/Assets/Bokeh__Lens_Dirt_50.jpg
PygameShader/Assets/Bokeh__Lens_Dirt_54.jpg
PygameShader/Assets/Bokeh__Lens_Dirt_67.jpg
PygameShader/Assets/Bokeh__Lens_Dirt_9.jpg
PygameShader/Assets/ES_WaterDrip1.wav
PygameShader/Assets/ES_WaterDrip2.wav
PygameShader/Assets/ES_WaterDrip3.wav
PygameShader/Assets/Parrot.jpg
PygameShader/Assets/Radial4.png
PygameShader/Assets/Radial8.png
PygameShader/Assets/alpha.png
pygameshader-1.0.11.dist-info/LICENSE
pygameshader-1.0.11.dist-info/METADATA
pygameshader-1.0.11.dist-info/WHEEL
pygameshader-1.0.11.dist-info/top_level.txt
pygameshader-1.0.11.dist-info/RECORD
