Metadata-Version: 2.1
Name: pygameshader
Version: 1.0.11
Summary: Pygame effects for 2D video game and arcade game
Home-page: https://github.com/yoyoberenguer/PygameShader
Author: Yoann Berenguer
Author-email: yoyoberenguer@hotmail.com
License: GNU General Public License v3.0
Project-URL: Bug Reports, https://github.com/yoyoberenguer/PygameShader/issues
Project-URL: Source, https://github.com/yoyoberenguer/PygameShader
Platform: Windows
Classifier: Development Status :: 4 - Beta
Classifier: Intended Audience :: Developers
Classifier: Intended Audience :: Education
Classifier: Intended Audience :: Science/Research
Classifier: Intended Audience :: End Users/Desktop
Classifier: Operating System :: Microsoft :: Windows
Classifier: Operating System :: POSIX :: Linux
Classifier: Operating System :: POSIX
Classifier: Operating System :: MacOS
Classifier: Programming Language :: Cython
Classifier: Programming Language :: C
Classifier: Programming Language :: C++
Classifier: Programming Language :: Python :: 3.6
Classifier: Programming Language :: Python :: 3.7
Classifier: Programming Language :: Python :: 3.8
Classifier: Programming Language :: Python :: 3.9
Classifier: Programming Language :: Python :: 3.10
Classifier: Programming Language :: Python :: 3.11
Classifier: Programming Language :: Python :: 3.12
Classifier: Programming Language :: Python :: 3.13
Classifier: License :: OSI Approved :: GNU General Public License v3 (GPLv3)
Classifier: Topic :: Software Development :: Libraries :: pygame
Classifier: Topic :: Software Development :: Build Tools
Requires-Python: >=3.6
License-File: LICENSE
Requires-Dist: setuptools >=49.2.1
Requires-Dist: Cython >=0.28
Requires-Dist: numpy >=1.18
Requires-Dist: pygame >=2.0
